pyqcisim/QCIS_inst.py
pyqcisim/QCIS_lexer.py
pyqcisim/QCIS_parser.py
pyqcisim/__init__.py
pyqcisim/circuit_executor.py
pyqcisim/circuit_executor_noisy_tequila.py
pyqcisim/circuit_executor_tequila.py
pyqcisim/parsetab.py
pyqcisim/qcis_to_openqasm.py
pyqcisim/simulate_qcis.py
pyqcisim/simulator.py
pyqcisim/utils.py
pyqcisim-1.3.7.dist-info/licenses/LICENSE
pyqcisim-1.3.7.dist-info/METADATA
pyqcisim-1.3.7.dist-info/WHEEL
pyqcisim-1.3.7.dist-info/top_level.txt
pyqcisim-1.3.7.dist-info/RECORD
