Metadata-Version: 2.4
Name: pyqcisim
Version: 1.3.7
Summary: A Python-based Quantum Control Instruction Set (QCIS) simulator
Home-page: https://gitee.com/hpcl_quanta/pyqcisim
Author: Zhihao Wu, Xiang Fu, Wenjin Chen
Author-email: gtaifu@gmail.com
Project-URL: Bug Tracker, https://gitee.com/hpcl_quanta/pyqcisim/issues
Classifier: Programming Language :: Python :: 3 :: Only
Classifier: License :: OSI Approved :: Apache Software License
Classifier: Operating System :: OS Independent
Requires-Python: >=3.7
License-File: LICENSE
Requires-Dist: quantumsim==0.2.0
Requires-Dist: bitstring
Requires-Dist: ply
Requires-Dist: numpy
Requires-Dist: pytest
Dynamic: license-file
